handit-0.0.1.dist-info/METADATA
handit-0.0.1.dist-info/WHEEL
handit_core/__init__.py
handit_core/__pycache__/__init__.cpython-310.pyc
handit_core/__pycache__/http_instrumentation.cpython-310.pyc
handit_core/handit_core_native.cpython-310-darwin.so
handit_core/http_instrumentation.py
handit-0.0.1.dist-info/RECORD
