Metadata-Version: 2.4
Name: handit
Version: 0.0.1
Classifier: Programming Language :: Python :: 3
Classifier: Programming Language :: Rust
Classifier: Operating System :: MacOS
Classifier: Operating System :: POSIX :: Linux
Classifier: Development Status :: 3 - Alpha
Author: Handit
License: Apache-2.0
Requires-Python: >=3.8
Project-URL: Homepage, https://example.com
